requirementscheck/__init__.py
requirementscheck/requirementscheck.py
requirementscheck/test_requirementscheck.py
requirementscheck-0.1.0.dist-info/licenses/LICENSE
requirementscheck-0.1.0.dist-info/METADATA
requirementscheck-0.1.0.dist-info/WHEEL
requirementscheck-0.1.0.dist-info/entry_points.txt
requirementscheck-0.1.0.dist-info/top_level.txt
requirementscheck-0.1.0.dist-info/RECORD
