Metadata-Version: 2.4
Name: RequirementsCheck
Version: 0.1.0
Summary: A CLI utility to check and update Python package versions in requirements.txt files
Home-page: https://github.com/bbilly1/requirementscheck
Author: Simon
Author-email: simobilleter@gmail.com
Classifier: Programming Language :: Python :: 3
Classifier: License :: OSI Approved :: MIT License
Classifier: Operating System :: OS Independent
Requires-Python: >=3.8
License-File: LICENSE
Requires-Dist: packaging
Dynamic: author
Dynamic: author-email
Dynamic: classifier
Dynamic: description
Dynamic: description-content-type
Dynamic: home-page
Dynamic: license-file
Dynamic: requires-dist
Dynamic: requires-python
Dynamic: summary
